README
setup.py
SelectScript/SelectExprLexer.py
SelectScript/SelectExprParser.py
SelectScript/SelectScript.py
SelectScript/SelectScript_Interpreter.py
SelectScript/__init__.py
SelectScript.egg-info/PKG-INFO
SelectScript.egg-info/SOURCES.txt
SelectScript.egg-info/dependency_links.txt
SelectScript.egg-info/requires.txt
SelectScript.egg-info/top_level.txt