Metadata-Version: 1.1
Name: SelectScript
Version: 0.1
Summary: Implementation of the query-language SelectScript for Python.
Home-page: https://pypi.python.org/pypi/SelectScript/0.1
Author: André Dietrich
Author-email: dietrich@ivs.cs.uni-magdeburg.de
License: BSD
Keywords: query,language
Platform: UNKNOWN
Classifier: Development Status :: 3 - Alpha
Classifier: Topic :: Utilities
Classifier: License :: OSI Approved :: BSD License
